rustc_t_x64_win_msvc_nightly_p5/__init__.py
rustc_t_x64_win_msvc_nightly_p5/data/rust-gdb
rustc_t_x64_win_msvc_nightly_p5/data/rust-gdbgui
rustc_t_x64_win_msvc_nightly_p5/data/rust-lldb
rustc_t_x64_win_msvc_nightly_p5/data/rust-windbg.cmd
rustc_t_x64_win_msvc_nightly_p5/data/rustc_main-57a55c5eedff6dbe.pdb
rustc_t_x64_win_msvc_nightly_p5/data/rustdoc.exe
rustc_t_x64_win_msvc_nightly_p5/data/rustdoc.pdb
rustc_t_x64_win_msvc_nightly_p5/data/std-e668b85dbbdbb3cf.dll
rustc_t_x64_win_msvc_nightly_p5/data/std-e668b85dbbdbb3cf.pdb
rustc_t_x64_win_msvc_nightly_p5-1.91.0.dist-info/METADATA
rustc_t_x64_win_msvc_nightly_p5-1.91.0.dist-info/WHEEL
rustc_t_x64_win_msvc_nightly_p5-1.91.0.dist-info/top_level.txt
rustc_t_x64_win_msvc_nightly_p5-1.91.0.dist-info/RECORD
